werkflow_http/__init__.py
werkflow_http/http.py
werkflow_http/request.py
werkflow_http/connections/__init__.py
werkflow_http/connections/http/__init__.py
werkflow_http/connections/http/mercury_sync_http_connection.py
werkflow_http/connections/http/timeouts.py
werkflow_http/connections/http/models/__init__.py
werkflow_http/connections/http/models/base/__init__.py
werkflow_http/connections/http/models/base/error.py
werkflow_http/connections/http/models/base/message.py
werkflow_http/connections/http/models/http/__init__.py
werkflow_http/connections/http/models/http/cookies.py
werkflow_http/connections/http/models/http/file.py
werkflow_http/connections/http/models/http/http_request.py
werkflow_http/connections/http/models/http/http_response.py
werkflow_http/connections/http/models/http/ip_address_info.py
werkflow_http/connections/http/models/http/metadata.py
werkflow_http/connections/http/models/http/types.py
werkflow_http/connections/http/models/http/url.py
werkflow_http/connections/http/models/http/url_metadata.py
werkflow_http/connections/http/protocols/__init__.py
werkflow_http/connections/http/protocols/connection.py
werkflow_http/connections/http/protocols/shared/__init__.py
werkflow_http/connections/http/protocols/shared/constants.py
werkflow_http/connections/http/protocols/shared/protocol.py
werkflow_http/connections/http/protocols/shared/reader.py
werkflow_http/connections/http/protocols/shared/writer.py
werkflow_http/connections/http/protocols/tcp/__init__.py
werkflow_http/connections/http/protocols/tcp/connection.py
werkflow_http/connections/http/protocols/tcp/protocol.py
werkflow_http/connections/http/protocols/tcp/tls_protocol.py
werkflow_http-0.6.3.dist-info/licenses/LICENSE
werkflow_http-0.6.3.dist-info/METADATA
werkflow_http-0.6.3.dist-info/WHEEL
werkflow_http-0.6.3.dist-info/top_level.txt
werkflow_http-0.6.3.dist-info/RECORD
