Metadata-Version: 2.4
Name: werkflow-http
Version: 0.6.3
Summary: An HTTP module for Werkflow.
Author-email: Ada Lundhe <adalundhe@lundhe.audio>
Keywords: pypi,cicd,python,werkflow,workflow,http,http1.1
Classifier: Programming Language :: Python :: 3.11
Classifier: Programming Language :: Python :: 3.12
Classifier: Programming Language :: Python :: 3.13
Classifier: Operating System :: OS Independent
Requires-Python: >=3.11
License-File: LICENSE
Requires-Dist: werkflow-core
Requires-Dist: werkflow-file
Requires-Dist: werkflow-secrets
Requires-Dist: werkflow-shell
Requires-Dist: werkflow-system
Requires-Dist: aiodns
Requires-Dist: orjson
Requires-Dist: pydantic
Dynamic: license-file
